wteleport/__init__.py
wteleport-0.0.0.dist-info/licenses/LICENSE
wteleport-0.0.0.dist-info/METADATA
wteleport-0.0.0.dist-info/WHEEL
wteleport-0.0.0.dist-info/top_level.txt
wteleport-0.0.0.dist-info/RECORD
