Metadata-Version: 2.4
Name: wteleport
Version: 0.0.0
Summary: The most convenient tool for working with telegram
Author-email: wisderfin <wisderfin@yandex.ru>
Project-URL: Homepage, https://github.com/wisderfin/wteleport
Project-URL: Bug Tracker, https://github.com/wisderfin/wteleport/issues
Requires-Python: >=3.10
License-File: LICENSE
Requires-Dist: requests
Requires-Dist: pytest
Dynamic: license-file
